ovos_stt_plugin_whisper_turbo/__init__.py
ovos_stt_plugin_whisper_turbo/version.py
ovos_stt_plugin_whisper_turbo-0.1.1.dist-info/LICENSE
ovos_stt_plugin_whisper_turbo-0.1.1.dist-info/METADATA
ovos_stt_plugin_whisper_turbo-0.1.1.dist-info/WHEEL
ovos_stt_plugin_whisper_turbo-0.1.1.dist-info/entry_points.txt
ovos_stt_plugin_whisper_turbo-0.1.1.dist-info/top_level.txt
ovos_stt_plugin_whisper_turbo-0.1.1.dist-info/zip-safe
ovos_stt_plugin_whisper_turbo-0.1.1.dist-info/RECORD
